django_raw_clearsessions/__init__.py
django_raw_clearsessions/cached_db.py
django_raw_clearsessions/db.py
django_raw_clearsessions-0.1.dist-info/METADATA
django_raw_clearsessions-0.1.dist-info/RECORD
django_raw_clearsessions-0.1.dist-info/WHEEL
django_raw_clearsessions-0.1.dist-info/top_level.txt
