Metadata-Version: 2.1
Name: django-raw-clearsessions
Version: 0.1
Summary: Efficiently clear expired sessions from the database.
Home-page: https://github.com/ixc/django-raw-clearsessions
Author: Interaction Consortium
Author-email: studio@interaction.net.au
License: MIT
Platform: UNKNOWN
